MercurySQLite/__init__.py
MercurySQLite/gensql.py
MercurySQLite-0.1.2.dist-info/LICENSE
MercurySQLite-0.1.2.dist-info/METADATA
MercurySQLite-0.1.2.dist-info/WHEEL
MercurySQLite-0.1.2.dist-info/top_level.txt
MercurySQLite-0.1.2.dist-info/RECORD
