Metadata-Version: 2.1
Name: MercurySQLite
Version: 0.1.2
Summary: Use built-in sqlite3 library to operate sql in a more pythonic way.
Home-page: https://github.com/BernieHuang2008/MercurySQLite
Author: Bernie J. Huang
Author-email: berniehuang2008@163.com
Classifier: Development Status :: 3 - Alpha
Classifier: Intended Audience :: Developers
Classifier: License :: OSI Approved :: MIT License
Classifier: Programming Language :: Python :: 3
Classifier: Programming Language :: Python :: 3.6
Classifier: Programming Language :: Python :: 3.7
Classifier: Programming Language :: Python :: 3.8
Classifier: Programming Language :: Python :: 3.9
License-File: LICENSE
